{"dataset":"all","q":"NL","issue":null,"sort":"amount_desc","page":1,"page_size":200,"total":506,"rows":[{"auction_date":"2009-08-22","single_line":"NL","double_line":null,"amount_hkd":340000,"pdf_url":"https://www.td.gov.hk/filemanager/tc/content_4806/pvrm%20auction%20result%20handout%20%2820090822%29.pdf","dataset_key":"pvrm","auction_key":"pvrm::2009-08-22"},{"auction_date":"2010-02-27","single_line":"0NLY U","double_line":["0NLY","U"],"amount_hkd":210000,"pdf_url":"https://www.td.gov.hk/filemanager/tc/content_4806/auctionresultshandout_20100227.pdf","dataset_key":"pvrm","auction_key":"pvrm::2010-02-27"},{"auction_date":"2015-12-20","single_line":"0NLY","double_line":null,"amount_hkd":105000,"pdf_url":"https://www.td.gov.hk/filemanager/common/auction_result_handout_2015-12-20.pdf","dataset_key":"pvrm","auction_key":"pvrm::2015-12-20"},{"auction_date":"2009-11-21","single_line":"NL 1","double_line":null,"amount_hkd":97000,"pdf_url":"./data/TVRM%20auction%20result%20%282006-2026%29.xlsx","source_url":"./data/TVRM%20auction%20result%20%282006-2026%29.xlsx","source_format":"xlsx","source_type":"xlsx_exact_dates","source_sheet":"2006-2009","result_status":"sold","result_text":"登記號碼在拍賣會中售出","date_precision":"day","auction_date_label":"2009-11-21","dataset_key":"tvrm_physical","auction_key":"tvrm_physical::2009-11-21"},{"auction_date":"2018-12-15","single_line":"NL 8","double_line":null,"amount_hkd":80000,"pdf_url":"./data/TVRM%20auction%20result%20%282006-2026%29.xlsx","source_url":"./data/TVRM%20auction%20result%20%282006-2026%29.xlsx","source_format":"xlsx","source_type":"xlsx_exact_dates","source_sheet":"2010-2019","result_status":"sold","result_text":"登記號碼在拍賣會中售出","date_precision":"day","auction_date_label":"2018-12-15","dataset_key":"tvrm_physical","auction_key":"tvrm_physical::2018-12-15"},{"auction_date":"2009-11-07","single_line":"NL 8","double_line":null,"amount_hkd":63000,"pdf_url":"./data/TVRM%20auction%20result%20%282006-2026%29.xlsx","source_url":"./data/TVRM%20auction%20result%20%282006-2026%29.xlsx","source_format":"xlsx","source_type":"xlsx_exact_dates","source_sheet":"2006-2009","result_status":"sold","result_text":"登記號碼在拍賣會中售出","date_precision":"day","auction_date_label":"2009-11-07","dataset_key":"tvrm_physical","auction_key":"tvrm_physical::2009-11-07"},{"auction_date":"2023-11-12","single_line":"MY 0NLY","double_line":null,"amount_hkd":60000,"pdf_url":"https://www.td.gov.hk/filemanager/tc/content_4806/pvrm_auction_result_20231112_chi.pdf","dataset_key":"pvrm","auction_key":"pvrm::2023-11-12"},{"auction_date":"2007-06-30","single_line":"0NLY Y0U","double_line":["0NLY","Y0U"],"amount_hkd":50000,"pdf_url":"https://www.td.gov.hk/filemanager/tc/content_4806/pvrm%20auction%20result%20%2820070630%29.pdf","dataset_key":"pvrm","auction_key":"pvrm::2007-06-30"},{"auction_date":"2015-12-05","single_line":"NL 9","double_line":null,"amount_hkd":48000,"pdf_url":"https://www.td.gov.hk/filemanager/common/auction%20result%20handout_2015.12.5.pdf","source_url":"./data/TVRM%20auction%20result%20%282006-2026%29.xlsx","source_format":"xlsx","source_type":"xlsx_exact_dates","source_sheet":"2010-2019","result_status":"sold","result_text":"登記號碼在拍賣會中售出","date_precision":"day","auction_date_label":"2015-12-05","dataset_key":"tvrm_physical","auction_key":"tvrm_physical::2015-12-05"},{"auction_date":"2016-03-12","single_line":"NL 168","double_line":null,"amount_hkd":44000,"pdf_url":"https://www.td.gov.hk/filemanager/common/tvrm%20auction%20handout_2016.3.12.pdf","source_url":"./data/TVRM%20auction%20result%20%282006-2026%29.xlsx","source_format":"xlsx","source_type":"xlsx_exact_dates","source_sheet":"2010-2019","result_status":"sold","result_text":"登記號碼在拍賣會中售出","date_precision":"day","auction_date_label":"2016-03-12","dataset_key":"tvrm_physical","auction_key":"tvrm_physical::2016-03-12"},{"auction_date":"2021-08-08","single_line":"0NLY ME","double_line":null,"amount_hkd":44000,"pdf_url":"https://www.td.gov.hk/filemanager/common/auction_result_20210808.pdf","dataset_key":"pvrm","auction_key":"pvrm::2021-08-08"},{"auction_date":"2010-01-09","single_line":"NL 3","double_line":null,"amount_hkd":42000,"pdf_url":"./data/TVRM%20auction%20result%20%282006-2026%29.xlsx","source_url":"./data/TVRM%20auction%20result%20%282006-2026%29.xlsx","source_format":"xlsx","source_type":"xlsx_exact_dates","source_sheet":"2010-2019","result_status":"sold","result_text":"登記號碼在拍賣會中售出","date_precision":"day","auction_date_label":"2010-01-09","dataset_key":"tvrm_physical","auction_key":"tvrm_physical::2010-01-09"},{"auction_date":"2010-08-28","single_line":"0NLY 0NE","double_line":["0NLY","0NE"],"amount_hkd":40000,"pdf_url":"https://www.td.gov.hk/filemanager/tc/content_4806/pvrm%20auction%20result%20handout%2028%20aug.pdf","dataset_key":"pvrm","auction_key":"pvrm::2010-08-28"},{"auction_date":"2009-09-20","single_line":"NL 7","double_line":null,"amount_hkd":37000,"pdf_url":"./data/TVRM%20auction%20result%20%282006-2026%29.xlsx","source_url":"./data/TVRM%20auction%20result%20%282006-2026%29.xlsx","source_format":"xlsx","source_type":"xlsx_exact_dates","source_sheet":"2006-2009","result_status":"sold","result_text":"登記號碼在拍賣會中售出","date_precision":"day","auction_date_label":"2009-09-20","dataset_key":"tvrm_physical","auction_key":"tvrm_physical::2009-09-20"},{"auction_date":"2022-08-06","single_line":"H1EN LEE","double_line":null,"amount_hkd":34000,"pdf_url":"https://www.td.gov.hk/filemanager/tc/content_4806/pvrm_auction_result_20220806.pdf","dataset_key":"pvrm","auction_key":"pvrm::2022-08-06"},{"auction_date":"2022-07-10","single_line":"THE 0NLY","double_line":null,"amount_hkd":32000,"pdf_url":"https://www.td.gov.hk/filemanager/tc/content_4806/result_20220710.pdf","dataset_key":"pvrm","auction_key":"pvrm::2022-07-10"},{"auction_date":"2019-09-08","single_line":"NL 9999","double_line":null,"amount_hkd":31000,"pdf_url":"./data/TVRM%20auction%20result%20%282006-2026%29.xlsx","source_url":"./data/TVRM%20auction%20result%20%282006-2026%29.xlsx","source_format":"xlsx","source_type":"xlsx_exact_dates","source_sheet":"2010-2019","result_status":"sold","result_text":"登記號碼在拍賣會中售出","date_precision":"day","auction_date_label":"2019-09-08","dataset_key":"tvrm_physical","auction_key":"tvrm_physical::2019-09-08"},{"auction_date":"2007-03-24","single_line":"STANLEY","double_line":null,"amount_hkd":30000,"pdf_url":"https://www.td.gov.hk/filemanager/tc/content_4806/auction%20result%20handout%2020070324.pdf","dataset_key":"pvrm","auction_key":"pvrm::2007-03-24"},{"auction_date":"2008-09-13","single_line":"NL 829","double_line":null,"amount_hkd":30000,"pdf_url":"./data/TVRM%20auction%20result%20%282006-2026%29.xlsx","source_url":"./data/TVRM%20auction%20result%20%282006-2026%29.xlsx","source_format":"xlsx","source_type":"xlsx_exact_dates","source_sheet":"2006-2009","result_status":"sold","result_text":"登記號碼在拍賣會中售出","date_precision":"day","auction_date_label":"2008-09-13","dataset_key":"tvrm_physical","auction_key":"tvrm_physical::2008-09-13"},{"auction_date":"2010-06-06","single_line":"NL 128","double_line":null,"amount_hkd":30000,"pdf_url":"./data/TVRM%20auction%20result%20%282006-2026%29.xlsx","source_url":"./data/TVRM%20auction%20result%20%282006-2026%29.xlsx","source_format":"xlsx","source_type":"xlsx_exact_dates","source_sheet":"2010-2019","result_status":"sold","result_text":"登記號碼在拍賣會中售出","date_precision":"day","auction_date_label":"2010-06-06","dataset_key":"tvrm_physical","auction_key":"tvrm_physical::2010-06-06"},{"auction_date":"2013-05-04","single_line":"0NLYL0VE","double_line":["0NLY","L0VE"],"amount_hkd":30000,"pdf_url":"https://www.td.gov.hk/filemanager/common/pvrm%20auction%20result%20handout%20%204%20may%202013.pdf","dataset_key":"pvrm","auction_key":"pvrm::2013-05-04"},{"auction_date":"2021-08-08","single_line":"NLC","double_line":null,"amount_hkd":30000,"pdf_url":"https://www.td.gov.hk/filemanager/common/auction_result_20210808.pdf","dataset_key":"pvrm","auction_key":"pvrm::2021-08-08"},{"auction_date":"2021-11-14","single_line":"NLB","double_line":null,"amount_hkd":30000,"pdf_url":"https://www.td.gov.hk/filemanager/common/pvrm_auction_result_14_11_2021.pdf","dataset_key":"pvrm","auction_key":"pvrm::2021-11-14"},{"auction_date":"2025-02-22","single_line":"ANS0N L0","double_line":null,"amount_hkd":30000,"pdf_url":"https://www.td.gov.hk/filemanager/tc/content_4806/pvrm_result_20250222_ch.pdf","dataset_key":"pvrm","auction_key":"pvrm::2025-02-22"},{"auction_date":"2025-06-14","single_line":"10NLY","double_line":["1","0NLY"],"amount_hkd":30000,"pdf_url":"https://www.td.gov.hk/filemanager/tc/content_4806/PVRMs%20Auction%20Result%20Handout%2014%20June%202025_Chin.pdf","dataset_key":"pvrm","auction_key":"pvrm::2025-06-14"},{"auction_date":"2019-10-13","single_line":"NL 288","double_line":null,"amount_hkd":29000,"pdf_url":"./data/TVRM%20auction%20result%20%282006-2026%29.xlsx","source_url":"./data/TVRM%20auction%20result%20%282006-2026%29.xlsx","source_format":"xlsx","source_type":"xlsx_exact_dates","source_sheet":"2010-2019","result_status":"sold","result_text":"登記號碼在拍賣會中售出","date_precision":"day","auction_date_label":"2019-10-13","dataset_key":"tvrm_physical","auction_key":"tvrm_physical::2019-10-13"},{"auction_date":"2009-05-17","single_line":"NL 88","double_line":null,"amount_hkd":28000,"pdf_url":"./data/TVRM%20auction%20result%20%282006-2026%29.xlsx","source_url":"./data/TVRM%20auction%20result%20%282006-2026%29.xlsx","source_format":"xlsx","source_type":"xlsx_exact_dates","source_sheet":"2006-2009","result_status":"sold","result_text":"登記號碼在拍賣會中售出","date_precision":"day","auction_date_label":"2009-05-17","dataset_key":"tvrm_physical","auction_key":"tvrm_physical::2009-05-17"},{"auction_date":"2012-06-16","single_line":"NL 328","double_line":null,"amount_hkd":28000,"pdf_url":"https://www.td.gov.hk/filemanager/common/20120616%20tvrm%20auction%20result.pdf","source_url":"./data/TVRM%20auction%20result%20%282006-2026%29.xlsx","source_format":"xlsx","source_type":"xlsx_exact_dates","source_sheet":"2010-2019","result_status":"sold","result_text":"登記號碼在拍賣會中售出","date_precision":"day","auction_date_label":"2012-06-16","dataset_key":"tvrm_physical","auction_key":"tvrm_physical::2012-06-16"},{"auction_date":"2009-10-10","single_line":"NL 18","double_line":null,"amount_hkd":27000,"pdf_url":"./data/TVRM%20auction%20result%20%282006-2026%29.xlsx","source_url":"./data/TVRM%20auction%20result%20%282006-2026%29.xlsx","source_format":"xlsx","source_type":"xlsx_exact_dates","source_sheet":"2006-2009","result_status":"sold","result_text":"登記號碼在拍賣會中售出","date_precision":"day","auction_date_label":"2009-10-10","dataset_key":"tvrm_physical","auction_key":"tvrm_physical::2009-10-10"},{"auction_date":"2006-12-02","single_line":"NLK","double_line":null,"amount_hkd":26000,"pdf_url":"https://www.td.gov.hk/filemanager/tc/content_4806/20061202pvrmret.pdf","dataset_key":"pvrm","auction_key":"pvrm::2006-12-02"},{"auction_date":"2021-06-19","single_line":"NL 138","double_line":null,"amount_hkd":26000,"pdf_url":"https://www.td.gov.hk/filemanager/common/tvrm_auction_result_19_6_2021.pdf","page":1,"dataset_key":"tvrm_physical","auction_key":"tvrm_physical::2021-06-19"},{"auction_date":"2021-07-03","single_line":"NL 13","double_line":null,"amount_hkd":26000,"pdf_url":"./data/TVRM%20auction%20result%20%282006-2026%29.xlsx","source_url":"./data/TVRM%20auction%20result%20%282006-2026%29.xlsx","source_format":"xlsx","source_type":"xlsx_exact_dates","source_sheet":"2020-2026","result_status":"sold","result_text":"登記號碼在拍賣會中售出","date_precision":"day","auction_date_label":"2021-07-03","dataset_key":"tvrm_physical","auction_key":"tvrm_physical::2021-07-03"},{"auction_date":"2010-08-28","single_line":"0NLY 1","double_line":["0NLY","1"],"amount_hkd":24000,"pdf_url":"https://www.td.gov.hk/filemanager/tc/content_4806/pvrm%20auction%20result%20handout%2028%20aug.pdf","dataset_key":"pvrm","auction_key":"pvrm::2010-08-28"},{"auction_date":"2026-02-26","single_line":"NL 388","double_line":null,"amount_hkd":23000,"pdf_url":"https://www.td.gov.hk/filemanager/en/content_4804/E-Auction%20Result%20Handout%2026%20February%20-%202%20March%202026.Eng.pdf","page":null,"dataset_key":"tvrm_eauction","auction_key":"tvrm_eauction::2026-02-26"},{"auction_date":"2026-02-26","single_line":"NL 388","double_line":null,"amount_hkd":23000,"pdf_url":"https://www.td.gov.hk/filemanager/tc/content_4804/E-Auction%20Result%20Handout%2026%20February%20-%202%20March%202026.Chin.pdf","page":null,"dataset_key":"tvrm_eauction","auction_key":"tvrm_eauction::2026-02-26"},{"auction_date":"2010-07-17","single_line":"NL 8888","double_line":null,"amount_hkd":22000,"pdf_url":"https://www.td.gov.hk/filemanager/common/auction%20results%20handout%20for%20tvrm%20auction_20100717.pdf","source_url":"./data/TVRM%20auction%20result%20%282006-2026%29.xlsx","source_format":"xlsx","source_type":"xlsx_exact_dates","source_sheet":"2010-2019","result_status":"sold","result_text":"登記號碼在拍賣會中售出","date_precision":"day","auction_date_label":"2010-07-17","dataset_key":"tvrm_physical","auction_key":"tvrm_physical::2010-07-17"},{"auction_date":"2016-08-21","single_line":"NL 6","double_line":null,"amount_hkd":22000,"pdf_url":"./data/TVRM%20auction%20result%20%282006-2026%29.xlsx","source_url":"./data/TVRM%20auction%20result%20%282006-2026%29.xlsx","source_format":"xlsx","source_type":"xlsx_exact_dates","source_sheet":"2010-2019","result_status":"sold","result_text":"登記號碼在拍賣會中售出","date_precision":"day","auction_date_label":"2016-08-21","dataset_key":"tvrm_physical","auction_key":"tvrm_physical::2016-08-21"},{"auction_date":"2019-12-14","single_line":"NL 5","double_line":null,"amount_hkd":22000,"pdf_url":"https://www.td.gov.hk/filemanager/common/tvrm%20auction%20result_14.12.2019.pdf","source_url":"./data/TVRM%20auction%20result%20%282006-2026%29.xlsx","source_format":"xlsx","source_type":"xlsx_exact_dates","source_sheet":"2010-2019","result_status":"sold","result_text":"登記號碼在拍賣會中售出","date_precision":"day","auction_date_label":"2019-12-14","dataset_key":"tvrm_physical","auction_key":"tvrm_physical::2019-12-14"},{"auction_date":"2024-09-08","single_line":"YUENL0NG","double_line":["YUEN","L0NG"],"amount_hkd":22000,"pdf_url":"https://www.td.gov.hk/filemanager/tc/content_4806/pvrm_result_20240908_ch.pdf","dataset_key":"pvrm","auction_key":"pvrm::2024-09-08"},{"auction_date":"2007-12-15","single_line":"SUNL1GHT","double_line":null,"amount_hkd":20000,"pdf_url":"https://www.td.gov.hk/filemanager/tc/content_4806/auction%20result%20handout_15%20dec%202007.pdf","dataset_key":"pvrm","auction_key":"pvrm::2007-12-15"},{"auction_date":"2010-06-05","single_line":"CNL","double_line":null,"amount_hkd":20000,"pdf_url":"https://www.td.gov.hk/filemanager/common/pvrm%20auction%20results%20handout_20100605.pdf","dataset_key":"pvrm","auction_key":"pvrm::2010-06-05"},{"auction_date":"2012-01-08","single_line":"1NL 0VE","double_line":null,"amount_hkd":20000,"pdf_url":"https://www.td.gov.hk/filemanager/tc/content_4806/pvrm%20result%20hadnout%208.1.2012.pdf","dataset_key":"pvrm","auction_key":"pvrm::2012-01-08"},{"auction_date":"2021-11-14","single_line":"KNL","double_line":null,"amount_hkd":20000,"pdf_url":"https://www.td.gov.hk/filemanager/common/pvrm_auction_result_14_11_2021.pdf","dataset_key":"pvrm","auction_key":"pvrm::2021-11-14"},{"auction_date":"2011-08-21","single_line":"NL 28","double_line":null,"amount_hkd":19000,"pdf_url":"https://www.td.gov.hk/filemanager/common/tvrm%20auction%20handout_20110821.pdf","source_url":"./data/TVRM%20auction%20result%20%282006-2026%29.xlsx","source_format":"xlsx","source_type":"xlsx_exact_dates","source_sheet":"2010-2019","result_status":"sold","result_text":"登記號碼在拍賣會中售出","date_precision":"day","auction_date_label":"2011-08-21","dataset_key":"tvrm_physical","auction_key":"tvrm_physical::2011-08-21"},{"auction_date":"2012-10-06","single_line":"NL 98","double_line":null,"amount_hkd":19000,"pdf_url":"https://www.td.gov.hk/filemanager/common/tvrm%20auction%20result%20handout%206-10-2012.pdf","source_url":"./data/TVRM%20auction%20result%20%282006-2026%29.xlsx","source_format":"xlsx","source_type":"xlsx_exact_dates","source_sheet":"2010-2019","result_status":"sold","result_text":"登記號碼在拍賣會中售出","date_precision":"day","auction_date_label":"2012-10-06","dataset_key":"tvrm_physical","auction_key":"tvrm_physical::2012-10-06"},{"auction_date":"2025-11-06","single_line":"NL 719","double_line":null,"amount_hkd":19000,"pdf_url":"https://www.td.gov.hk/filemanager/tc/content_4804/E-Auction%20Result%20Handout%206-10%20November%202025.Chin.pdf","page":null,"dataset_key":"tvrm_eauction","auction_key":"tvrm_eauction::2025-11-06"},{"auction_date":"2010-01-31","single_line":"NL 888","double_line":null,"amount_hkd":18000,"pdf_url":"./data/TVRM%20auction%20result%20%282006-2026%29.xlsx","source_url":"./data/TVRM%20auction%20result%20%282006-2026%29.xlsx","source_format":"xlsx","source_type":"xlsx_exact_dates","source_sheet":"2010-2019","result_status":"sold","result_text":"登記號碼在拍賣會中售出","date_precision":"day","auction_date_label":"2010-01-31","dataset_key":"tvrm_physical","auction_key":"tvrm_physical::2010-01-31"},{"auction_date":"2021-09-26","single_line":"NL 2888","double_line":null,"amount_hkd":18000,"pdf_url":"https://www.td.gov.hk/filemanager/common/tvrm_result_20210926.pdf","page":1,"dataset_key":"tvrm_physical","auction_key":"tvrm_physical::2021-09-26"},{"auction_date":"2024-03-09","single_line":"NL 333","double_line":null,"amount_hkd":18000,"pdf_url":"https://www.td.gov.hk/filemanager/en/content_4804/tvrm_auction_result_20240309_en.pdf","page":2,"dataset_key":"tvrm_physical","auction_key":"tvrm_physical::2024-03-09"},{"auction_date":"2024-03-09","single_line":"NL 333","double_line":null,"amount_hkd":18000,"pdf_url":"https://www.td.gov.hk/filemanager/tc/content_4804/tvrm_auction_result_20240309_chi.pdf","page":2,"dataset_key":"tvrm_physical","auction_key":"tvrm_physical::2024-03-09"},{"auction_date":"2010-06-05","single_line":"TNL","double_line":null,"amount_hkd":17000,"pdf_url":"https://www.td.gov.hk/filemanager/common/pvrm%20auction%20results%20handout_20100605.pdf","dataset_key":"pvrm","auction_key":"pvrm::2010-06-05"},{"auction_date":"2012-05-19","single_line":"NL 2","double_line":null,"amount_hkd":17000,"pdf_url":"https://www.td.gov.hk/filemanager/common/tvrm%20auction%20result%20handout%2019-5-2012.pdf","source_url":"./data/TVRM%20auction%20result%20%282006-2026%29.xlsx","source_format":"xlsx","source_type":"xlsx_exact_dates","source_sheet":"2010-2019","result_status":"sold","result_text":"登記號碼在拍賣會中售出","date_precision":"day","auction_date_label":"2012-05-19","dataset_key":"tvrm_physical","auction_key":"tvrm_physical::2012-05-19"},{"auction_date":"2017-09-02","single_line":"BEN L","double_line":null,"amount_hkd":17000,"pdf_url":"https://www.td.gov.hk/filemanager/common/pvrm_auction%20result_2017.9.2.pdf","dataset_key":"pvrm","auction_key":"pvrm::2017-09-02"},{"auction_date":"2018-11-11","single_line":"ANL","double_line":null,"amount_hkd":17000,"pdf_url":"https://www.td.gov.hk/filemanager/common/pvrm-auctionresult2018-11-11.pdf","dataset_key":"pvrm","auction_key":"pvrm::2018-11-11"},{"auction_date":"2022-08-28","single_line":"0NL1NE","double_line":null,"amount_hkd":17000,"pdf_url":"https://www.td.gov.hk/filemanager/tc/content_4806/pvrm_auction_result_20220828.pdf","dataset_key":"pvrm","auction_key":"pvrm::2022-08-28"},{"auction_date":"2015-01-11","single_line":"NL 188","double_line":null,"amount_hkd":16000,"pdf_url":"https://www.td.gov.hk/filemanager/common/tvrm%20auction%20result%20handout_11.1.2015.pdf","source_url":"./data/TVRM%20auction%20result%20%282006-2026%29.xlsx","source_format":"xlsx","source_type":"xlsx_exact_dates","source_sheet":"2010-2019","result_status":"sold","result_text":"登記號碼在拍賣會中售出","date_precision":"day","auction_date_label":"2015-01-11","dataset_key":"tvrm_physical","auction_key":"tvrm_physical::2015-01-11"},{"auction_date":"2019-06-02","single_line":"NL 66","double_line":null,"amount_hkd":16000,"pdf_url":"https://www.td.gov.hk/filemanager/common/tvrm%20auction%20result_2019.6.2.pdf","source_url":"./data/TVRM%20auction%20result%20%282006-2026%29.xlsx","source_format":"xlsx","source_type":"xlsx_exact_dates","source_sheet":"2010-2019","result_status":"sold","result_text":"登記號碼在拍賣會中售出","date_precision":"day","auction_date_label":"2019-06-02","dataset_key":"tvrm_physical","auction_key":"tvrm_physical::2019-06-02"},{"auction_date":"2019-09-01","single_line":"NL 33","double_line":null,"amount_hkd":16000,"pdf_url":"https://www.td.gov.hk/filemanager/common/tvrm%20auction%20result_2019.9.1.pdf","source_url":"./data/TVRM%20auction%20result%20%282006-2026%29.xlsx","source_format":"xlsx","source_type":"xlsx_exact_dates","source_sheet":"2010-2019","result_status":"sold","result_text":"登記號碼在拍賣會中售出","date_precision":"day","auction_date_label":"2019-09-01","dataset_key":"tvrm_physical","auction_key":"tvrm_physical::2019-09-01"},{"auction_date":"2026-01-04","single_line":"GUANLAN","double_line":null,"amount_hkd":16000,"pdf_url":"https://www.td.gov.hk/filemanager/tc/content_4806/pvrm_result_20260104_ch.pdf","dataset_key":"pvrm","auction_key":"pvrm::2026-01-04"},{"auction_date":"2006-09-16","single_line":"BEN LEE","double_line":null,"amount_hkd":15000,"pdf_url":"https://www.td.gov.hk/filemanager/tc/content_4806/20060916pvrmret.pdf","dataset_key":"pvrm","auction_key":"pvrm::2006-09-16"},{"auction_date":"2012-12-09","single_line":"NL 22","double_line":null,"amount_hkd":15000,"pdf_url":"https://www.td.gov.hk/filemanager/common/20121209%20tvrm%20auction%20result.pdf","source_url":"./data/TVRM%20auction%20result%20%282006-2026%29.xlsx","source_format":"xlsx","source_type":"xlsx_exact_dates","source_sheet":"2010-2019","result_status":"sold","result_text":"登記號碼在拍賣會中售出","date_precision":"day","auction_date_label":"2012-12-09","dataset_key":"tvrm_physical","auction_key":"tvrm_physical::2012-12-09"},{"auction_date":"2015-08-02","single_line":"NL 44","double_line":null,"amount_hkd":15000,"pdf_url":"https://www.td.gov.hk/filemanager/common/tvrm%20auction%20result%20handout_2.8.2015.pdf","source_url":"./data/TVRM%20auction%20result%20%282006-2026%29.xlsx","source_format":"xlsx","source_type":"xlsx_exact_dates","source_sheet":"2010-2019","result_status":"sold","result_text":"登記號碼在拍賣會中售出","date_precision":"day","auction_date_label":"2015-08-02","dataset_key":"tvrm_physical","auction_key":"tvrm_physical::2015-08-02"},{"auction_date":"2016-04-10","single_line":"NL 822","double_line":null,"amount_hkd":15000,"pdf_url":"https://www.td.gov.hk/filemanager/common/20160410%20tvrm%20auction%20result.pdf","source_url":"./data/TVRM%20auction%20result%20%282006-2026%29.xlsx","source_format":"xlsx","source_type":"xlsx_exact_dates","source_sheet":"2010-2019","result_status":"sold","result_text":"登記號碼在拍賣會中售出","date_precision":"day","auction_date_label":"2016-04-10","dataset_key":"tvrm_physical","auction_key":"tvrm_physical::2016-04-10"},{"auction_date":"2019-05-18","single_line":"NL 38","double_line":null,"amount_hkd":15000,"pdf_url":"./data/TVRM%20auction%20result%20%282006-2026%29.xlsx","source_url":"./data/TVRM%20auction%20result%20%282006-2026%29.xlsx","source_format":"xlsx","source_type":"xlsx_exact_dates","source_sheet":"2010-2019","result_status":"sold","result_text":"登記號碼在拍賣會中售出","date_precision":"day","auction_date_label":"2019-05-18","dataset_key":"tvrm_physical","auction_key":"tvrm_physical::2019-05-18"},{"auction_date":"2023-12-03","single_line":"H1NS0N L","double_line":null,"amount_hkd":15000,"pdf_url":"https://www.td.gov.hk/filemanager/tc/content_4806/pvrm_auction_result_20231203_chi.pdf","dataset_key":"pvrm","auction_key":"pvrm::2023-12-03"},{"auction_date":"2018-01-27","single_line":"41N L0VE","double_line":["4 1N","L0VE"],"amount_hkd":14000,"pdf_url":"https://www.td.gov.hk/filemanager/common/pvrm%20auction%20result_2018.1.27.pdf","dataset_key":"pvrm","auction_key":"pvrm::2018-01-27"},{"auction_date":"2008-09-06","single_line":"NL 113","double_line":null,"amount_hkd":13000,"pdf_url":"./data/TVRM%20auction%20result%20%282006-2026%29.xlsx","source_url":"./data/TVRM%20auction%20result%20%282006-2026%29.xlsx","source_format":"xlsx","source_type":"xlsx_exact_dates","source_sheet":"2006-2009","result_status":"sold","result_text":"登記號碼在拍賣會中售出","date_precision":"day","auction_date_label":"2008-09-06","dataset_key":"tvrm_physical","auction_key":"tvrm_physical::2008-09-06"},{"auction_date":"2019-04-06","single_line":"NL 20","double_line":null,"amount_hkd":13000,"pdf_url":"./data/TVRM%20auction%20result%20%282006-2026%29.xlsx","source_url":"./data/TVRM%20auction%20result%20%282006-2026%29.xlsx","source_format":"xlsx","source_type":"xlsx_exact_dates","source_sheet":"2010-2019","result_status":"sold","result_text":"登記號碼在拍賣會中售出","date_precision":"day","auction_date_label":"2019-04-06","dataset_key":"tvrm_physical","auction_key":"tvrm_physical::2019-04-06"},{"auction_date":"2021-08-07","single_line":"NL 11","double_line":null,"amount_hkd":13000,"pdf_url":"https://www.td.gov.hk/filemanager/common/tvrm_auction_result_7_8_2021.pdf","page":1,"dataset_key":"tvrm_physical","auction_key":"tvrm_physical::2021-08-07"},{"auction_date":"2008-09-06","single_line":"NL 228","double_line":null,"amount_hkd":12000,"pdf_url":"./data/TVRM%20auction%20result%20%282006-2026%29.xlsx","source_url":"./data/TVRM%20auction%20result%20%282006-2026%29.xlsx","source_format":"xlsx","source_type":"xlsx_exact_dates","source_sheet":"2006-2009","result_status":"sold","result_text":"登記號碼在拍賣會中售出","date_precision":"day","auction_date_label":"2008-09-06","dataset_key":"tvrm_physical","auction_key":"tvrm_physical::2008-09-06"},{"auction_date":"2009-10-31","single_line":"NLW","double_line":null,"amount_hkd":12000,"pdf_url":"https://www.td.gov.hk/filemanager/tc/content_4806/pvrm%20auction%20result%20handout%20%2820091031%29.pdf","dataset_key":"pvrm","auction_key":"pvrm::2009-10-31"},{"auction_date":"2011-06-19","single_line":"NL 882","double_line":null,"amount_hkd":12000,"pdf_url":"https://www.td.gov.hk/filemanager/common/tvrm%20auction%20handout_20110619.pdf","source_url":"./data/TVRM%20auction%20result%20%282006-2026%29.xlsx","source_format":"xlsx","source_type":"xlsx_exact_dates","source_sheet":"2010-2019","result_status":"sold","result_text":"登記號碼在拍賣會中售出","date_precision":"day","auction_date_label":"2011-06-19","dataset_key":"tvrm_physical","auction_key":"tvrm_physical::2011-06-19"},{"auction_date":"2018-07-08","single_line":"NL 68","double_line":null,"amount_hkd":12000,"pdf_url":"https://www.td.gov.hk/filemanager/common/tvrm%20auction%20result_2018.7.8.pdf","source_url":"./data/TVRM%20auction%20result%20%282006-2026%29.xlsx","source_format":"xlsx","source_type":"xlsx_exact_dates","source_sheet":"2010-2019","result_status":"sold","result_text":"登記號碼在拍賣會中售出","date_precision":"day","auction_date_label":"2018-07-08","dataset_key":"tvrm_physical","auction_key":"tvrm_physical::2018-07-08"},{"auction_date":"2023-12-16","single_line":"UP0NLY","double_line":null,"amount_hkd":12000,"pdf_url":"https://www.td.gov.hk/filemanager/tc/content_4806/pvrm_result_20231216_ch.pdf","dataset_key":"pvrm","auction_key":"pvrm::2023-12-16"},{"auction_date":"2007-12-15","single_line":"BR1AN L","double_line":["BR1A","N L"],"amount_hkd":11000,"pdf_url":"https://www.td.gov.hk/filemanager/tc/content_4806/auction%20result%20handout_15%20dec%202007.pdf","dataset_key":"pvrm","auction_key":"pvrm::2007-12-15"},{"auction_date":"2017-11-25","single_line":"X NL X","double_line":null,"amount_hkd":11000,"pdf_url":"https://www.td.gov.hk/filemanager/common/pvrm%20auction%20result_2017.11.25.pdf","dataset_key":"pvrm","auction_key":"pvrm::2017-11-25"},{"auction_date":"2021-12-11","single_line":"NL 8883","double_line":null,"amount_hkd":11000,"pdf_url":"https://www.td.gov.hk/filemanager/common/tvrm_auction_result_11_12_2021.pdf","page":1,"dataset_key":"tvrm_physical","auction_key":"tvrm_physical::2021-12-11"},{"auction_date":"2008-08-30","single_line":"LNL","double_line":null,"amount_hkd":10000,"pdf_url":"https://www.td.gov.hk/filemanager/tc/content_4806/pvrm%20auction%20result%20handout%20%2820080830%29.pdf","dataset_key":"pvrm","auction_key":"pvrm::2008-08-30"},{"auction_date":"2008-09-06","single_line":"NL 218","double_line":null,"amount_hkd":10000,"pdf_url":"./data/TVRM%20auction%20result%20%282006-2026%29.xlsx","source_url":"./data/TVRM%20auction%20result%20%282006-2026%29.xlsx","source_format":"xlsx","source_type":"xlsx_exact_dates","source_sheet":"2006-2009","result_status":"sold","result_text":"登記號碼在拍賣會中售出","date_precision":"day","auction_date_label":"2008-09-06","dataset_key":"tvrm_physical","auction_key":"tvrm_physical::2008-09-06"},{"auction_date":"2013-11-17","single_line":"NL 3288","double_line":null,"amount_hkd":10000,"pdf_url":"https://www.td.gov.hk/filemanager/common/tvrm%20auction%20result%20handout_17.11.2013.pdf","source_url":"./data/TVRM%20auction%20result%20%282006-2026%29.xlsx","source_format":"xlsx","source_type":"xlsx_exact_dates","source_sheet":"2010-2019","result_status":"sold","result_text":"登記號碼在拍賣會中售出","date_precision":"day","auction_date_label":"2013-11-17","dataset_key":"tvrm_physical","auction_key":"tvrm_physical::2013-11-17"},{"auction_date":"2016-03-12","single_line":"NL 8868","double_line":null,"amount_hkd":10000,"pdf_url":"https://www.td.gov.hk/filemanager/common/tvrm%20auction%20handout_2016.3.12.pdf","source_url":"./data/TVRM%20auction%20result%20%282006-2026%29.xlsx","source_format":"xlsx","source_type":"xlsx_exact_dates","source_sheet":"2010-2019","result_status":"sold","result_text":"登記號碼在拍賣會中售出","date_precision":"day","auction_date_label":"2016-03-12","dataset_key":"tvrm_physical","auction_key":"tvrm_physical::2016-03-12"},{"auction_date":"2016-10-22","single_line":"NLY","double_line":null,"amount_hkd":10000,"pdf_url":"https://www.td.gov.hk/filemanager/common/pvrm-auction-result-handout-2016-10-22.pdf","dataset_key":"pvrm","auction_key":"pvrm::2016-10-22"},{"auction_date":"2017-06-03","single_line":"NL 133","double_line":null,"amount_hkd":10000,"pdf_url":"./data/TVRM%20auction%20result%20%282006-2026%29.xlsx","source_url":"./data/TVRM%20auction%20result%20%282006-2026%29.xlsx","source_format":"xlsx","source_type":"xlsx_exact_dates","source_sheet":"2010-2019","result_status":"sold","result_text":"登記號碼在拍賣會中售出","date_precision":"day","auction_date_label":"2017-06-03","dataset_key":"tvrm_physical","auction_key":"tvrm_physical::2017-06-03"},{"auction_date":"2017-06-10","single_line":"NL 83","double_line":null,"amount_hkd":10000,"pdf_url":"./data/TVRM%20auction%20result%20%282006-2026%29.xlsx","source_url":"./data/TVRM%20auction%20result%20%282006-2026%29.xlsx","source_format":"xlsx","source_type":"xlsx_exact_dates","source_sheet":"2010-2019","result_status":"sold","result_text":"登記號碼在拍賣會中售出","date_precision":"day","auction_date_label":"2017-06-10","dataset_key":"tvrm_physical","auction_key":"tvrm_physical::2017-06-10"},{"auction_date":"2017-11-12","single_line":"NL LN","double_line":["N L","LN"],"amount_hkd":10000,"pdf_url":"https://www.td.gov.hk/filemanager/common/pvrm2017-11-12auctionresult.pdf","dataset_key":"pvrm","auction_key":"pvrm::2017-11-12"},{"auction_date":"2018-11-03","single_line":"NL 1111","double_line":null,"amount_hkd":10000,"pdf_url":"https://www.td.gov.hk/filemanager/common/tvrm%20auction%20result_2018.11.3.pdf","source_url":"./data/TVRM%20auction%20result%20%282006-2026%29.xlsx","source_format":"xlsx","source_type":"xlsx_exact_dates","source_sheet":"2010-2019","result_status":"sold","result_text":"登記號碼在拍賣會中售出","date_precision":"day","auction_date_label":"2018-11-03","dataset_key":"tvrm_physical","auction_key":"tvrm_physical::2018-11-03"},{"auction_date":"2024-01-27","single_line":"NL 163","double_line":null,"amount_hkd":10000,"pdf_url":"https://www.td.gov.hk/filemanager/en/content_4804/tvrm_auction_result_20240127_en.pdf","page":1,"dataset_key":"tvrm_physical","auction_key":"tvrm_physical::2024-01-27"},{"auction_date":"2024-01-27","single_line":"NL 163","double_line":null,"amount_hkd":10000,"pdf_url":"https://www.td.gov.hk/filemanager/sc/content_4804/tvrm_auction_result_20240127_ch.pdf","page":1,"dataset_key":"tvrm_physical","auction_key":"tvrm_physical::2024-01-27"},{"auction_date":"2012-01-08","single_line":"NLT","double_line":null,"amount_hkd":9000,"pdf_url":"https://www.td.gov.hk/filemanager/tc/content_4806/pvrm%20result%20hadnout%208.1.2012.pdf","dataset_key":"pvrm","auction_key":"pvrm::2012-01-08"},{"auction_date":"2015-03-29","single_line":"NL 531","double_line":null,"amount_hkd":9000,"pdf_url":"https://www.td.gov.hk/filemanager/common/20150329%20tvrm%20auction%20result.pdf","source_url":"./data/TVRM%20auction%20result%20%282006-2026%29.xlsx","source_format":"xlsx","source_type":"xlsx_exact_dates","source_sheet":"2010-2019","result_status":"sold","result_text":"登記號碼在拍賣會中售出","date_precision":"day","auction_date_label":"2015-03-29","dataset_key":"tvrm_physical","auction_key":"tvrm_physical::2015-03-29"},{"auction_date":"2015-10-17","single_line":"LNLN","double_line":["LN","LN"],"amount_hkd":9000,"pdf_url":"https://www.td.gov.hk/filemanager/common/pvrm_auction_result_handout_20151017.pdf","dataset_key":"pvrm","auction_key":"pvrm::2015-10-17"},{"auction_date":"2016-08-20","single_line":"NL 79","double_line":null,"amount_hkd":9000,"pdf_url":"./data/TVRM%20auction%20result%20%282006-2026%29.xlsx","source_url":"./data/TVRM%20auction%20result%20%282006-2026%29.xlsx","source_format":"xlsx","source_type":"xlsx_exact_dates","source_sheet":"2010-2019","result_status":"sold","result_text":"登記號碼在拍賣會中售出","date_precision":"day","auction_date_label":"2016-08-20","dataset_key":"tvrm_physical","auction_key":"tvrm_physical::2016-08-20"},{"auction_date":"2023-12-16","single_line":"T 0NLY","double_line":null,"amount_hkd":9000,"pdf_url":"https://www.td.gov.hk/filemanager/tc/content_4806/pvrm_result_20231216_ch.pdf","dataset_key":"pvrm","auction_key":"pvrm::2023-12-16"},{"auction_date":"2024-06-01","single_line":"NL 828","double_line":null,"amount_hkd":9000,"pdf_url":"https://www.td.gov.hk/filemanager/en/content_4804/tvrm_auction_result_20240601_en.pdf","page":2,"dataset_key":"tvrm_physical","auction_key":"tvrm_physical::2024-06-01"},{"auction_date":"2024-06-01","single_line":"NL 828","double_line":null,"amount_hkd":9000,"pdf_url":"https://www.td.gov.hk/filemanager/tc/content_4804/tvrm_auction_result_20240601_chi.pdf","page":2,"dataset_key":"tvrm_physical","auction_key":"tvrm_physical::2024-06-01"},{"auction_date":"2024-10-27","single_line":"0NLYG0","double_line":["0NLY","G0"],"amount_hkd":9000,"pdf_url":"https://www.td.gov.hk/filemanager/tc/content_4806/pvrm_result_20241027_ch.pdf","dataset_key":"pvrm","auction_key":"pvrm::2024-10-27"},{"auction_date":"2007-01-20","single_line":"BENLY","double_line":null,"amount_hkd":8000,"pdf_url":"https://www.td.gov.hk/filemanager/tc/content_4806/20070120pvrmret.pdf","dataset_key":"pvrm","auction_key":"pvrm::2007-01-20"},{"auction_date":"2008-10-26","single_line":"NL 1221","double_line":null,"amount_hkd":8000,"pdf_url":"./data/TVRM%20auction%20result%20%282006-2026%29.xlsx","source_url":"./data/TVRM%20auction%20result%20%282006-2026%29.xlsx","source_format":"xlsx","source_type":"xlsx_exact_dates","source_sheet":"2006-2009","result_status":"sold","result_text":"登記號碼在拍賣會中售出","date_precision":"day","auction_date_label":"2008-10-26","dataset_key":"tvrm_physical","auction_key":"tvrm_physical::2008-10-26"},{"auction_date":"2009-01-11","single_line":"NL 17","double_line":null,"amount_hkd":8000,"pdf_url":"./data/TVRM%20auction%20result%20%282006-2026%29.xlsx","source_url":"./data/TVRM%20auction%20result%20%282006-2026%29.xlsx","source_format":"xlsx","source_type":"xlsx_exact_dates","source_sheet":"2006-2009","result_status":"sold","result_text":"登記號碼在拍賣會中售出","date_precision":"day","auction_date_label":"2009-01-11","dataset_key":"tvrm_physical","auction_key":"tvrm_physical::2009-01-11"},{"auction_date":"2009-06-27","single_line":"JNL","double_line":null,"amount_hkd":8000,"pdf_url":"https://www.td.gov.hk/filemanager/en/content_4806/auction%20results%20handout%20for%20pvrm%20auction%20held%20on%2020090627.pdf","dataset_key":"pvrm","auction_key":"pvrm::2009-06-27"},{"auction_date":"2014-07-12","single_line":"NL 618","double_line":null,"amount_hkd":8000,"pdf_url":"./data/TVRM%20auction%20result%20%282006-2026%29.xlsx","source_url":"./data/TVRM%20auction%20result%20%282006-2026%29.xlsx","source_format":"xlsx","source_type":"xlsx_exact_dates","source_sheet":"2010-2019","result_status":"sold","result_text":"登記號碼在拍賣會中售出","date_precision":"day","auction_date_label":"2014-07-12","dataset_key":"tvrm_physical","auction_key":"tvrm_physical::2014-07-12"},{"auction_date":"2022-11-20","single_line":"ANS0N L","double_line":null,"amount_hkd":8000,"pdf_url":"https://www.td.gov.hk/filemanager/tc/content_4806/pvrm_auction_result_20221120_CHI.pdf","dataset_key":"pvrm","auction_key":"pvrm::2022-11-20"},{"auction_date":"2024-04-06","single_line":"NL 14","double_line":null,"amount_hkd":8000,"pdf_url":"https://www.td.gov.hk/filemanager/en/content_4804/tvrm_auction_result_20240406_en.pdf","page":1,"dataset_key":"tvrm_physical","auction_key":"tvrm_physical::2024-04-06"},{"auction_date":"2024-04-06","single_line":"NL 14","double_line":null,"amount_hkd":8000,"pdf_url":"https://www.td.gov.hk/filemanager/tc/content_4804/tvrm_auction_result_20240406_chi.pdf","page":1,"dataset_key":"tvrm_physical","auction_key":"tvrm_physical::2024-04-06"},{"auction_date":"2008-09-06","single_line":"NL 208","double_line":null,"amount_hkd":7000,"pdf_url":"./data/TVRM%20auction%20result%20%282006-2026%29.xlsx","source_url":"./data/TVRM%20auction%20result%20%282006-2026%29.xlsx","source_format":"xlsx","source_type":"xlsx_exact_dates","source_sheet":"2006-2009","result_status":"sold","result_text":"登記號碼在拍賣會中售出","date_precision":"day","auction_date_label":"2008-09-06","dataset_key":"tvrm_physical","auction_key":"tvrm_physical::2008-09-06"},{"auction_date":"2008-09-06","single_line":"NL 332","double_line":null,"amount_hkd":7000,"pdf_url":"./data/TVRM%20auction%20result%20%282006-2026%29.xlsx","source_url":"./data/TVRM%20auction%20result%20%282006-2026%29.xlsx","source_format":"xlsx","source_type":"xlsx_exact_dates","source_sheet":"2006-2009","result_status":"sold","result_text":"登記號碼在拍賣會中售出","date_precision":"day","auction_date_label":"2008-09-06","dataset_key":"tvrm_physical","auction_key":"tvrm_physical::2008-09-06"},{"auction_date":"2008-09-13","single_line":"NL 223","double_line":null,"amount_hkd":7000,"pdf_url":"./data/TVRM%20auction%20result%20%282006-2026%29.xlsx","source_url":"./data/TVRM%20auction%20result%20%282006-2026%29.xlsx","source_format":"xlsx","source_type":"xlsx_exact_dates","source_sheet":"2006-2009","result_status":"sold","result_text":"登記號碼在拍賣會中售出","date_precision":"day","auction_date_label":"2008-09-13","dataset_key":"tvrm_physical","auction_key":"tvrm_physical::2008-09-13"},{"auction_date":"2010-01-31","single_line":"NL 15","double_line":null,"amount_hkd":7000,"pdf_url":"./data/TVRM%20auction%20result%20%282006-2026%29.xlsx","source_url":"./data/TVRM%20auction%20result%20%282006-2026%29.xlsx","source_format":"xlsx","source_type":"xlsx_exact_dates","source_sheet":"2010-2019","result_status":"sold","result_text":"登記號碼在拍賣會中售出","date_precision":"day","auction_date_label":"2010-01-31","dataset_key":"tvrm_physical","auction_key":"tvrm_physical::2010-01-31"},{"auction_date":"2011-05-28","single_line":"KEN L","double_line":["KEN","L"],"amount_hkd":7000,"pdf_url":"https://www.td.gov.hk/filemanager/common/pvrm%20auction%20result%20handout_20110528.pdf","dataset_key":"pvrm","auction_key":"pvrm::2011-05-28"},{"auction_date":"2012-11-24","single_line":"NL 1010","double_line":null,"amount_hkd":7000,"pdf_url":"./data/TVRM%20auction%20result%20%282006-2026%29.xlsx","source_url":"./data/TVRM%20auction%20result%20%282006-2026%29.xlsx","source_format":"xlsx","source_type":"xlsx_exact_dates","source_sheet":"2010-2019","result_status":"sold","result_text":"登記號碼在拍賣會中售出","date_precision":"day","auction_date_label":"2012-11-24","dataset_key":"tvrm_physical","auction_key":"tvrm_physical::2012-11-24"},{"auction_date":"2015-08-29","single_line":"NL 1118","double_line":null,"amount_hkd":7000,"pdf_url":"https://www.td.gov.hk/filemanager/common/20150829%20tvrm%20auction%20result.pdf","source_url":"./data/TVRM%20auction%20result%20%282006-2026%29.xlsx","source_format":"xlsx","source_type":"xlsx_exact_dates","source_sheet":"2010-2019","result_status":"sold","result_text":"登記號碼在拍賣會中售出","date_precision":"day","auction_date_label":"2015-08-29","dataset_key":"tvrm_physical","auction_key":"tvrm_physical::2015-08-29"},{"auction_date":"2016-03-19","single_line":"MNL","double_line":null,"amount_hkd":7000,"pdf_url":"https://www.td.gov.hk/filemanager/common/auction%20result%20handout_2016.03.19.pdf","dataset_key":"pvrm","auction_key":"pvrm::2016-03-19"},{"auction_date":"2016-11-13","single_line":"L1N L1N","double_line":["L1N","L1N"],"amount_hkd":7000,"pdf_url":"https://www.td.gov.hk/filemanager/common/pvrm-auction-result-handout-2016-11-13.pdf","dataset_key":"pvrm","auction_key":"pvrm::2016-11-13"},{"auction_date":"2018-08-04","single_line":"NL 17","double_line":null,"amount_hkd":7000,"pdf_url":"https://www.td.gov.hk/filemanager/common/tvrm%20auction%20result_2018.8.4.pdf","source_url":"./data/TVRM%20auction%20result%20%282006-2026%29.xlsx","source_format":"xlsx","source_type":"xlsx_exact_dates","source_sheet":"2010-2019","result_status":"sold","result_text":"登記號碼在拍賣會中售出","date_precision":"day","auction_date_label":"2018-08-04","dataset_key":"tvrm_physical","auction_key":"tvrm_physical::2018-08-04"},{"auction_date":"2018-12-01","single_line":"NL 92","double_line":null,"amount_hkd":7000,"pdf_url":"./data/TVRM%20auction%20result%20%282006-2026%29.xlsx","source_url":"./data/TVRM%20auction%20result%20%282006-2026%29.xlsx","source_format":"xlsx","source_type":"xlsx_exact_dates","source_sheet":"2010-2019","result_status":"sold","result_text":"登記號碼在拍賣會中售出","date_precision":"day","auction_date_label":"2018-12-01","dataset_key":"tvrm_physical","auction_key":"tvrm_physical::2018-12-01"},{"auction_date":"2019-04-06","single_line":"NL 139","double_line":null,"amount_hkd":7000,"pdf_url":"./data/TVRM%20auction%20result%20%282006-2026%29.xlsx","source_url":"./data/TVRM%20auction%20result%20%282006-2026%29.xlsx","source_format":"xlsx","source_type":"xlsx_exact_dates","source_sheet":"2010-2019","result_status":"sold","result_text":"登記號碼在拍賣會中售出","date_precision":"day","auction_date_label":"2019-04-06","dataset_key":"tvrm_physical","auction_key":"tvrm_physical::2019-04-06"},{"auction_date":"2023-01-15","single_line":"NL 444","double_line":null,"amount_hkd":7000,"pdf_url":"./data/TVRM%20auction%20result%20%282006-2026%29.xlsx","source_url":"./data/TVRM%20auction%20result%20%282006-2026%29.xlsx","source_format":"xlsx","source_type":"xlsx_exact_dates","source_sheet":"2020-2026","result_status":"sold","result_text":"登記號碼在拍賣會中售出","date_precision":"day","auction_date_label":"2023-01-15","dataset_key":"tvrm_physical","auction_key":"tvrm_physical::2023-01-15"},{"auction_date":"2023-03-26","single_line":"NLC9","double_line":["NLC","9"],"amount_hkd":7000,"pdf_url":"https://www.td.gov.hk/filemanager/tc/content_4806/pvrm_auction_result_20230326_ch.pdf","dataset_key":"pvrm","auction_key":"pvrm::2023-03-26"},{"auction_date":"2024-06-01","single_line":"NL 95","double_line":null,"amount_hkd":7000,"pdf_url":"https://www.td.gov.hk/filemanager/en/content_4804/tvrm_auction_result_20240601_en.pdf","page":1,"dataset_key":"tvrm_physical","auction_key":"tvrm_physical::2024-06-01"},{"auction_date":"2024-06-01","single_line":"NL 95","double_line":null,"amount_hkd":7000,"pdf_url":"https://www.td.gov.hk/filemanager/tc/content_4804/tvrm_auction_result_20240601_chi.pdf","page":1,"dataset_key":"tvrm_physical","auction_key":"tvrm_physical::2024-06-01"},{"auction_date":"2013-08-04","single_line":"NL 30","double_line":null,"amount_hkd":6000,"pdf_url":"./data/TVRM%20auction%20result%20%282006-2026%29.xlsx","source_url":"./data/TVRM%20auction%20result%20%282006-2026%29.xlsx","source_format":"xlsx","source_type":"xlsx_exact_dates","source_sheet":"2010-2019","result_status":"sold","result_text":"登記號碼在拍賣會中售出","date_precision":"day","auction_date_label":"2013-08-04","dataset_key":"tvrm_physical","auction_key":"tvrm_physical::2013-08-04"},{"auction_date":"2015-04-26","single_line":"NL 666","double_line":null,"amount_hkd":6000,"pdf_url":"https://www.td.gov.hk/filemanager/common/tvrm%20auction%20result%20handout_26.4.2015.pdf","source_url":"./data/TVRM%20auction%20result%20%282006-2026%29.xlsx","source_format":"xlsx","source_type":"xlsx_exact_dates","source_sheet":"2010-2019","result_status":"sold","result_text":"登記號碼在拍賣會中售出","date_precision":"day","auction_date_label":"2015-04-26","dataset_key":"tvrm_physical","auction_key":"tvrm_physical::2015-04-26"},{"auction_date":"2015-08-23","single_line":"NL 777","double_line":null,"amount_hkd":6000,"pdf_url":"https://www.td.gov.hk/filemanager/common/tvrm-auction-result-handout-2015-08-23.pdf","source_url":"./data/TVRM%20auction%20result%20%282006-2026%29.xlsx","source_format":"xlsx","source_type":"xlsx_exact_dates","source_sheet":"2010-2019","result_status":"sold","result_text":"登記號碼在拍賣會中售出","date_precision":"day","auction_date_label":"2015-08-23","dataset_key":"tvrm_physical","auction_key":"tvrm_physical::2015-08-23"},{"auction_date":"2015-10-04","single_line":"NL 12","double_line":null,"amount_hkd":6000,"pdf_url":"https://www.td.gov.hk/filemanager/common/auction%20result%20handout_4.10.2015.pdf","source_url":"./data/TVRM%20auction%20result%20%282006-2026%29.xlsx","source_format":"xlsx","source_type":"xlsx_exact_dates","source_sheet":"2010-2019","result_status":"sold","result_text":"登記號碼在拍賣會中售出","date_precision":"day","auction_date_label":"2015-10-04","dataset_key":"tvrm_physical","auction_key":"tvrm_physical::2015-10-04"},{"auction_date":"2016-03-06","single_line":"NL 20","double_line":null,"amount_hkd":6000,"pdf_url":"https://www.td.gov.hk/filemanager/common/auction%20result%20handout_2016.3.6.pdf","source_url":"./data/TVRM%20auction%20result%20%282006-2026%29.xlsx","source_format":"xlsx","source_type":"xlsx_exact_dates","source_sheet":"2010-2019","result_status":"sold","result_text":"登記號碼在拍賣會中售出","date_precision":"day","auction_date_label":"2016-03-06","dataset_key":"tvrm_physical","auction_key":"tvrm_physical::2016-03-06"},{"auction_date":"2017-06-03","single_line":"NL 132","double_line":null,"amount_hkd":6000,"pdf_url":"./data/TVRM%20auction%20result%20%282006-2026%29.xlsx","source_url":"./data/TVRM%20auction%20result%20%282006-2026%29.xlsx","source_format":"xlsx","source_type":"xlsx_exact_dates","source_sheet":"2010-2019","result_status":"sold","result_text":"登記號碼在拍賣會中售出","date_precision":"day","auction_date_label":"2017-06-03","dataset_key":"tvrm_physical","auction_key":"tvrm_physical::2017-06-03"},{"auction_date":"2018-03-24","single_line":"NL 59","double_line":null,"amount_hkd":6000,"pdf_url":"./data/TVRM%20auction%20result%20%282006-2026%29.xlsx","source_url":"./data/TVRM%20auction%20result%20%282006-2026%29.xlsx","source_format":"xlsx","source_type":"xlsx_exact_dates","source_sheet":"2010-2019","result_status":"sold","result_text":"登記號碼在拍賣會中售出","date_precision":"day","auction_date_label":"2018-03-24","dataset_key":"tvrm_physical","auction_key":"tvrm_physical::2018-03-24"},{"auction_date":"2023-02-26","single_line":"NL 110","double_line":null,"amount_hkd":6000,"pdf_url":"https://www.td.gov.hk/filemanager/en/content_4804/tvrm_auction_result_20230226_en.pdf","page":2,"dataset_key":"tvrm_physical","auction_key":"tvrm_physical::2023-02-26"},{"auction_date":"2023-02-26","single_line":"NL 110","double_line":null,"amount_hkd":6000,"pdf_url":"https://www.td.gov.hk/filemanager/sc/content_4804/tvrm_auction_result_20230226_ch.pdf","page":2,"dataset_key":"tvrm_physical","auction_key":"tvrm_physical::2023-02-26"},{"auction_date":"2024-12-07","single_line":"NL 85","double_line":null,"amount_hkd":6000,"pdf_url":"https://www.td.gov.hk/filemanager/en/content_4804/tvrm_auction_result_20241207_en.pdf","page":2,"dataset_key":"tvrm_physical","auction_key":"tvrm_physical::2024-12-07"},{"auction_date":"2024-12-07","single_line":"NL 85","double_line":null,"amount_hkd":6000,"pdf_url":"https://www.td.gov.hk/filemanager/tc/content_4804/tvrm_auction_result_20241207_chi.pdf","page":2,"dataset_key":"tvrm_physical","auction_key":"tvrm_physical::2024-12-07"},{"auction_date":"2025-10-25","single_line":"NL 54","double_line":null,"amount_hkd":6000,"pdf_url":"https://www.td.gov.hk/filemanager/en/content_4804/tvrm_auction_result_20251025_en.pdf","page":1,"dataset_key":"tvrm_physical","auction_key":"tvrm_physical::2025-10-25"},{"auction_date":"2025-10-25","single_line":"NL 54","double_line":null,"amount_hkd":6000,"pdf_url":"https://www.td.gov.hk/filemanager/tc/content_4804/tvrm_auction_result_20251025_chi.pdf","page":1,"dataset_key":"tvrm_physical","auction_key":"tvrm_physical::2025-10-25"},{"auction_date":"2006-09-16","single_line":"1AN L1","double_line":["1AN","L1"],"amount_hkd":5000,"pdf_url":"https://www.td.gov.hk/filemanager/tc/content_4806/20060916pvrmret.pdf","dataset_key":"pvrm","auction_key":"pvrm::2006-09-16"},{"auction_date":"2006-09-16","single_line":"EDW1N L0","double_line":null,"amount_hkd":5000,"pdf_url":"https://www.td.gov.hk/filemanager/tc/content_4806/20060916pvrmret.pdf","dataset_key":"pvrm","auction_key":"pvrm::2006-09-16"},{"auction_date":"2006-10-28","single_line":"T1ENLUNG","double_line":["T1EN","LUNG"],"amount_hkd":5000,"pdf_url":"https://www.td.gov.hk/filemanager/tc/content_4806/20061028pvrmret.pdf","dataset_key":"pvrm","auction_key":"pvrm::2006-10-28"},{"auction_date":"2006-12-02","single_line":"NGANLUNG","double_line":["NGAN","LUNG"],"amount_hkd":5000,"pdf_url":"https://www.td.gov.hk/filemanager/tc/content_4806/20061202pvrmret.pdf","dataset_key":"pvrm","auction_key":"pvrm::2006-12-02"},{"auction_date":"2007-05-05","single_line":"YUN LEE1","double_line":null,"amount_hkd":5000,"pdf_url":"https://www.td.gov.hk/filemanager/tc/content_4806/auction%20result%20handout%20%28070505%29.pdf","dataset_key":"pvrm","auction_key":"pvrm::2007-05-05"},{"auction_date":"2007-06-30","single_line":"ANLEV","double_line":null,"amount_hkd":5000,"pdf_url":"https://www.td.gov.hk/filemanager/tc/content_4806/pvrm%20auction%20result%20%2820070630%29.pdf","dataset_key":"pvrm","auction_key":"pvrm::2007-06-30"},{"auction_date":"2007-06-30","single_line":"KAN LA1","double_line":["KAN","LA1"],"amount_hkd":5000,"pdf_url":"https://www.td.gov.hk/filemanager/tc/content_4806/pvrm%20auction%20result%20%2820070630%29.pdf","dataset_key":"pvrm","auction_key":"pvrm::2007-06-30"},{"auction_date":"2007-08-04","single_line":"1VANL0RA","double_line":["1VAN","L0RA"],"amount_hkd":5000,"pdf_url":"https://www.td.gov.hk/filemanager/tc/content_4806/pvrm%20auction%20aug%204-%20auction%20result%20handout%20-%20icc.pdf","dataset_key":"pvrm","auction_key":"pvrm::2007-08-04"},{"auction_date":"2007-10-27","single_line":"KEV1NLAM","double_line":null,"amount_hkd":5000,"pdf_url":"https://www.td.gov.hk/filemanager/tc/content_4806/pvrm%20auction%20result%20handout%20oct%2027.pdf","dataset_key":"pvrm","auction_key":"pvrm::2007-10-27"},{"auction_date":"2007-10-27","single_line":"S0NLEY","double_line":null,"amount_hkd":5000,"pdf_url":"https://www.td.gov.hk/filemanager/tc/content_4806/pvrm%20auction%20result%20handout%20oct%2027.pdf","dataset_key":"pvrm","auction_key":"pvrm::2007-10-27"},{"auction_date":"2007-12-15","single_line":"ANL 123","double_line":["ANL","123"],"amount_hkd":5000,"pdf_url":"https://www.td.gov.hk/filemanager/tc/content_4806/auction%20result%20handout_15%20dec%202007.pdf","dataset_key":"pvrm","auction_key":"pvrm::2007-12-15"},{"auction_date":"2007-12-15","single_line":"CN L1FE","double_line":null,"amount_hkd":5000,"pdf_url":"https://www.td.gov.hk/filemanager/tc/content_4806/auction%20result%20handout_15%20dec%202007.pdf","dataset_key":"pvrm","auction_key":"pvrm::2007-12-15"},{"auction_date":"2008-04-12","single_line":"GENL1N 1","double_line":null,"amount_hkd":5000,"pdf_url":"https://www.td.gov.hk/filemanager/tc/content_4806/20080412pvrmret.pdf","dataset_key":"pvrm","auction_key":"pvrm::2008-04-12"},{"auction_date":"2008-04-12","single_line":"GENL1N66","double_line":null,"amount_hkd":5000,"pdf_url":"https://www.td.gov.hk/filemanager/tc/content_4806/20080412pvrmret.pdf","dataset_key":"pvrm","auction_key":"pvrm::2008-04-12"},{"auction_date":"2008-05-24","single_line":"S1M0NLAW","double_line":null,"amount_hkd":5000,"pdf_url":"https://www.td.gov.hk/filemanager/tc/content_4806/pvrm%20auction%20result%20handout%2020080524.pdf","dataset_key":"pvrm","auction_key":"pvrm::2008-05-24"},{"auction_date":"2008-06-14","single_line":"DAN LAM","double_line":["DAN","LAM"],"amount_hkd":5000,"pdf_url":"https://www.td.gov.hk/filemanager/tc/content_4806/auction%20results%20handout%20of%20pvrm%20auction%20on%2020080614.pdf","dataset_key":"pvrm","auction_key":"pvrm::2008-06-14"},{"auction_date":"2008-06-14","single_line":"MAN L0NG","double_line":["MAN","L0NG"],"amount_hkd":5000,"pdf_url":"https://www.td.gov.hk/filemanager/tc/content_4806/auction%20results%20handout%20of%20pvrm%20auction%20on%2020080614.pdf","dataset_key":"pvrm","auction_key":"pvrm::2008-06-14"},{"auction_date":"2008-08-30","single_line":"JAS0NLEE","double_line":null,"amount_hkd":5000,"pdf_url":"https://www.td.gov.hk/filemanager/tc/content_4806/pvrm%20auction%20result%20handout%20%2820080830%29.pdf","dataset_key":"pvrm","auction_key":"pvrm::2008-08-30"},{"auction_date":"2008-09-06","single_line":"NL 117","double_line":null,"amount_hkd":5000,"pdf_url":"./data/TVRM%20auction%20result%20%282006-2026%29.xlsx","source_url":"./data/TVRM%20auction%20result%20%282006-2026%29.xlsx","source_format":"xlsx","source_type":"xlsx_exact_dates","source_sheet":"2006-2009","result_status":"sold","result_text":"登記號碼在拍賣會中售出","date_precision":"day","auction_date_label":"2008-09-06","dataset_key":"tvrm_physical","auction_key":"tvrm_physical::2008-09-06"},{"auction_date":"2008-09-06","single_line":"NL 119","double_line":null,"amount_hkd":5000,"pdf_url":"./data/TVRM%20auction%20result%20%282006-2026%29.xlsx","source_url":"./data/TVRM%20auction%20result%20%282006-2026%29.xlsx","source_format":"xlsx","source_type":"xlsx_exact_dates","source_sheet":"2006-2009","result_status":"sold","result_text":"登記號碼在拍賣會中售出","date_precision":"day","auction_date_label":"2008-09-06","dataset_key":"tvrm_physical","auction_key":"tvrm_physical::2008-09-06"},{"auction_date":"2008-10-04","single_line":"0NLYME28","double_line":null,"amount_hkd":5000,"pdf_url":"https://www.td.gov.hk/filemanager/tc/content_4806/auction%20results%20handout%20of%20pvrm%20auction%20%284%20oct%202008%29.pdf","dataset_key":"pvrm","auction_key":"pvrm::2008-10-04"},{"auction_date":"2008-11-01","single_line":"SUN LEE","double_line":["SUN","LEE"],"amount_hkd":5000,"pdf_url":"https://www.td.gov.hk/filemanager/tc/content_4806/pvrm%20auction%20result%20handout%20%2820081101%29.pdf","dataset_key":"pvrm","auction_key":"pvrm::2008-11-01"},{"auction_date":"2008-11-02","single_line":"NL 398","double_line":null,"amount_hkd":5000,"pdf_url":"./data/TVRM%20auction%20result%20%282006-2026%29.xlsx","source_url":"./data/TVRM%20auction%20result%20%282006-2026%29.xlsx","source_format":"xlsx","source_type":"xlsx_exact_dates","source_sheet":"2006-2009","result_status":"sold","result_text":"登記號碼在拍賣會中售出","date_precision":"day","auction_date_label":"2008-11-02","dataset_key":"tvrm_physical","auction_key":"tvrm_physical::2008-11-02"},{"auction_date":"2008-12-07","single_line":"HENL0RD","double_line":["HEN","L0RD"],"amount_hkd":5000,"pdf_url":"https://www.td.gov.hk/filemanager/tc/content_4806/pvrm%20auction%20result%20handout%20%2820081207%29.pdf","dataset_key":"pvrm","auction_key":"pvrm::2008-12-07"},{"auction_date":"2009-01-17","single_line":"X NLK X","double_line":null,"amount_hkd":5000,"pdf_url":"https://www.td.gov.hk/filemanager/tc/content_4806/auction%20results%20handout%20of%20pvrm%20auction%20%2820090117%29.pdf","dataset_key":"pvrm","auction_key":"pvrm::2009-01-17"},{"auction_date":"2009-02-28","single_line":"KEN LAM","double_line":["KEN","LAM"],"amount_hkd":5000,"pdf_url":"https://www.td.gov.hk/filemanager/tc/content_4806/pvrm%20auction%20result%20handout%2020090228.pdf","dataset_key":"pvrm","auction_key":"pvrm::2009-02-28"},{"auction_date":"2009-03-21","single_line":"W1NL0K","double_line":["W1N","L0K"],"amount_hkd":5000,"pdf_url":"https://www.td.gov.hk/filemanager/tc/content_4806/pvrm%20auction%20result%20handout%20%2820090321%29.pdf","dataset_key":"pvrm","auction_key":"pvrm::2009-03-21"},{"auction_date":"2009-04-05","single_line":"KEENLEX","double_line":["KEEN","LEX"],"amount_hkd":5000,"pdf_url":"https://www.td.gov.hk/filemanager/tc/content_4806/pvrm%20auction%20result%20handout%20%2820090405%29.pdf","dataset_key":"pvrm","auction_key":"pvrm::2009-04-05"},{"auction_date":"2009-05-23","single_line":"MEGANLAM","double_line":null,"amount_hkd":5000,"pdf_url":"https://www.td.gov.hk/filemanager/tc/content_4806/pvrm%20auction%20result%20handout%20%2820090523%29.pdf","dataset_key":"pvrm","auction_key":"pvrm::2009-05-23"},{"auction_date":"2009-05-23","single_line":"W1NL0YAL","double_line":null,"amount_hkd":5000,"pdf_url":"https://www.td.gov.hk/filemanager/tc/content_4806/pvrm%20auction%20result%20handout%20%2820090523%29.pdf","dataset_key":"pvrm","auction_key":"pvrm::2009-05-23"},{"auction_date":"2009-06-27","single_line":"DEAC0NL0","double_line":null,"amount_hkd":5000,"pdf_url":"https://www.td.gov.hk/filemanager/en/content_4806/auction%20results%20handout%20for%20pvrm%20auction%20held%20on%2020090627.pdf","dataset_key":"pvrm","auction_key":"pvrm::2009-06-27"},{"auction_date":"2009-07-18","single_line":"BENL1LEE","double_line":null,"amount_hkd":5000,"pdf_url":"https://www.td.gov.hk/filemanager/tc/content_4806/pvrm%20auction%20result%20handout%20%2820090718%29.pdf","dataset_key":"pvrm","auction_key":"pvrm::2009-07-18"},{"auction_date":"2009-07-18","single_line":"J0HN L1","double_line":["J0HN","L1"],"amount_hkd":5000,"pdf_url":"https://www.td.gov.hk/filemanager/tc/content_4806/pvrm%20auction%20result%20handout%20%2820090718%29.pdf","dataset_key":"pvrm","auction_key":"pvrm::2009-07-18"},{"auction_date":"2009-08-22","single_line":"ANL 318","double_line":["ANL","318"],"amount_hkd":5000,"pdf_url":"https://www.td.gov.hk/filemanager/tc/content_4806/pvrm%20auction%20result%20handout%20%2820090822%29.pdf","dataset_key":"pvrm","auction_key":"pvrm::2009-08-22"},{"auction_date":"2009-08-22","single_line":"LUN LUN","double_line":["LUN","LUN"],"amount_hkd":5000,"pdf_url":"https://www.td.gov.hk/filemanager/tc/content_4806/pvrm%20auction%20result%20handout%20%2820090822%29.pdf","dataset_key":"pvrm","auction_key":"pvrm::2009-08-22"},{"auction_date":"2009-08-22","single_line":"S1M0NLA1","double_line":null,"amount_hkd":5000,"pdf_url":"https://www.td.gov.hk/filemanager/tc/content_4806/pvrm%20auction%20result%20handout%20%2820090822%29.pdf","dataset_key":"pvrm","auction_key":"pvrm::2009-08-22"},{"auction_date":"2009-10-31","single_line":"G1DE0N L","double_line":null,"amount_hkd":5000,"pdf_url":"https://www.td.gov.hk/filemanager/tc/content_4806/pvrm%20auction%20result%20handout%20%2820091031%29.pdf","dataset_key":"pvrm","auction_key":"pvrm::2009-10-31"},{"auction_date":"2009-10-31","single_line":"J1NL1","double_line":null,"amount_hkd":5000,"pdf_url":"https://www.td.gov.hk/filemanager/tc/content_4806/pvrm%20auction%20result%20handout%20%2820091031%29.pdf","dataset_key":"pvrm","auction_key":"pvrm::2009-10-31"},{"auction_date":"2010-01-09","single_line":"NL 27","double_line":null,"amount_hkd":5000,"pdf_url":"./data/TVRM%20auction%20result%20%282006-2026%29.xlsx","source_url":"./data/TVRM%20auction%20result%20%282006-2026%29.xlsx","source_format":"xlsx","source_type":"xlsx_exact_dates","source_sheet":"2010-2019","result_status":"sold","result_text":"登記號碼在拍賣會中售出","date_precision":"day","auction_date_label":"2010-01-09","dataset_key":"tvrm_physical","auction_key":"tvrm_physical::2010-01-09"},{"auction_date":"2010-02-27","single_line":"MANLEY","double_line":null,"amount_hkd":5000,"pdf_url":"https://www.td.gov.hk/filemanager/tc/content_4806/auctionresultshandout_20100227.pdf","dataset_key":"pvrm","auction_key":"pvrm::2010-02-27"},{"auction_date":"2010-02-27","single_line":"YUNLEE28","double_line":null,"amount_hkd":5000,"pdf_url":"https://www.td.gov.hk/filemanager/tc/content_4806/auctionresultshandout_20100227.pdf","dataset_key":"pvrm","auction_key":"pvrm::2010-02-27"},{"auction_date":"2010-03-21","single_line":"CANLUM","double_line":["CAN","LUM"],"amount_hkd":5000,"pdf_url":"https://www.td.gov.hk/filemanager/tc/content_4806/pvrmauctionresultshandout_20100321.pdf","dataset_key":"pvrm","auction_key":"pvrm::2010-03-21"},{"auction_date":"2010-05-08","single_line":"T1N L0K","double_line":["T1N","L0K"],"amount_hkd":5000,"pdf_url":"https://www.td.gov.hk/filemanager/tc/content_4806/auctionresultshandout_20100508.pdf","dataset_key":"pvrm","auction_key":"pvrm::2010-05-08"},{"auction_date":"2010-07-10","single_line":"BA1ANL1","double_line":null,"amount_hkd":5000,"pdf_url":"https://www.td.gov.hk/filemanager/tc/content_4806/auction_result_handout_10_7_2010.pdf","dataset_key":"pvrm","auction_key":"pvrm::2010-07-10"},{"auction_date":"2010-07-10","single_line":"D0N L0","double_line":["D0N","L0"],"amount_hkd":5000,"pdf_url":"https://www.td.gov.hk/filemanager/tc/content_4806/auction_result_handout_10_7_2010.pdf","dataset_key":"pvrm","auction_key":"pvrm::2010-07-10"},{"auction_date":"2010-09-04","single_line":"NL1K","double_line":null,"amount_hkd":5000,"pdf_url":"https://www.td.gov.hk/filemanager/common/pvrm%20auction%20results%20handout_20100904.pdf","dataset_key":"pvrm","auction_key":"pvrm::2010-09-04"},{"auction_date":"2010-11-14","single_line":"JNL1","double_line":null,"amount_hkd":5000,"pdf_url":"https://www.td.gov.hk/filemanager/common/pvrm%20auction%20results%20handout_20101114.pdf","dataset_key":"pvrm","auction_key":"pvrm::2010-11-14"},{"auction_date":"2010-11-14","single_line":"SUN LUNG","double_line":["SUN","LUNG"],"amount_hkd":5000,"pdf_url":"https://www.td.gov.hk/filemanager/common/pvrm%20auction%20results%20handout_20101114.pdf","dataset_key":"pvrm","auction_key":"pvrm::2010-11-14"},{"auction_date":"2010-12-12","single_line":"KWANLAM8","double_line":["KWAN","LAM8"],"amount_hkd":5000,"pdf_url":"https://www.td.gov.hk/filemanager/tc/content_4806/tvrm_auction_result_handout_12dec2010.pdf","dataset_key":"pvrm","auction_key":"pvrm::2010-12-12"},{"auction_date":"2011-01-08","single_line":"S1M0NLSM","double_line":null,"amount_hkd":5000,"pdf_url":"https://www.td.gov.hk/filemanager/common/auction%20results%20handout_20110108.pdf","dataset_key":"pvrm","auction_key":"pvrm::2011-01-08"},{"auction_date":"2011-02-19","single_line":"RYAN LA1","double_line":["RYAN","LA1"],"amount_hkd":5000,"pdf_url":"https://www.td.gov.hk/filemanager/common/pvrm%20auction%20results%20handout_20110219.pdf","dataset_key":"pvrm","auction_key":"pvrm::2011-02-19"},{"auction_date":"2011-05-28","single_line":"J0AN LA1","double_line":["J0AN","LA1"],"amount_hkd":5000,"pdf_url":"https://www.td.gov.hk/filemanager/common/pvrm%20auction%20result%20handout_20110528.pdf","dataset_key":"pvrm","auction_key":"pvrm::2011-05-28"},{"auction_date":"2011-05-28","single_line":"VAN LA1","double_line":["VAN","LA1"],"amount_hkd":5000,"pdf_url":"https://www.td.gov.hk/filemanager/common/pvrm%20auction%20result%20handout_20110528.pdf","dataset_key":"pvrm","auction_key":"pvrm::2011-05-28"},{"auction_date":"2011-06-18","single_line":"VANL0S","double_line":null,"amount_hkd":5000,"pdf_url":"https://www.td.gov.hk/filemanager/common/20110618%20pvrm%20auction%20result.pdf","dataset_key":"pvrm","auction_key":"pvrm::2011-06-18"},{"auction_date":"2011-07-17","single_line":"SHUNLUEN","double_line":["SHUN","LUEN"],"amount_hkd":5000,"pdf_url":"https://www.td.gov.hk/filemanager/common/pvrm%20auction%20reult%2017_7_2011.pdf","dataset_key":"pvrm","auction_key":"pvrm::2011-07-17"},{"auction_date":"2011-07-17","single_line":"VANL0","double_line":["VAN","L0"],"amount_hkd":5000,"pdf_url":"https://www.td.gov.hk/filemanager/common/pvrm%20auction%20reult%2017_7_2011.pdf","dataset_key":"pvrm","auction_key":"pvrm::2011-07-17"},{"auction_date":"2011-09-17","single_line":"B0NB0NL0","double_line":["B0NB","0NL0"],"amount_hkd":5000,"pdf_url":"https://www.td.gov.hk/filemanager/common/pvrms%20auction%20result%20handout%20%2820110917%29.pdf","dataset_key":"pvrm","auction_key":"pvrm::2011-09-17"},{"auction_date":"2011-09-17","single_line":"HANJ1NL0","double_line":null,"amount_hkd":5000,"pdf_url":"https://www.td.gov.hk/filemanager/common/pvrms%20auction%20result%20handout%20%2820110917%29.pdf","dataset_key":"pvrm","auction_key":"pvrm::2011-09-17"},{"auction_date":"2011-09-17","single_line":"HENLEY","double_line":null,"amount_hkd":5000,"pdf_url":"https://www.td.gov.hk/filemanager/common/pvrms%20auction%20result%20handout%20%2820110917%29.pdf","dataset_key":"pvrm","auction_key":"pvrm::2011-09-17"},{"auction_date":"2011-10-29","single_line":"MAN L0K","double_line":["MAN","L0K"],"amount_hkd":5000,"pdf_url":"https://www.td.gov.hk/filemanager/common/pvrm%20auction%20result%2020111029.pdf","dataset_key":"pvrm","auction_key":"pvrm::2011-10-29"},{"auction_date":"2011-10-29","single_line":"MANL1 8","double_line":null,"amount_hkd":5000,"pdf_url":"https://www.td.gov.hk/filemanager/common/pvrm%20auction%20result%2020111029.pdf","dataset_key":"pvrm","auction_key":"pvrm::2011-10-29"},{"auction_date":"2011-11-27","single_line":"0NLY CAN","double_line":null,"amount_hkd":5000,"pdf_url":"https://www.td.gov.hk/filemanager/common/pvrm%20auction%20result%2020111127.pdf","dataset_key":"pvrm","auction_key":"pvrm::2011-11-27"},{"auction_date":"2012-02-11","single_line":"JNL2","double_line":null,"amount_hkd":5000,"pdf_url":"https://www.td.gov.hk/filemanager/common/pvrm%20auction%20result%20handout%2011.2.2012.pdf","dataset_key":"pvrm","auction_key":"pvrm::2012-02-11"},{"auction_date":"2012-03-10","single_line":"17N NL1","double_line":["17N","NL1"],"amount_hkd":5000,"pdf_url":"https://www.td.gov.hk/filemanager/common/pvrm%20auction%20result%20handout%2010.3.2012.pdf","dataset_key":"pvrm","auction_key":"pvrm::2012-03-10"},{"auction_date":"2012-03-31","single_line":"0CEAN L","double_line":["0CE","AN L"],"amount_hkd":5000,"pdf_url":"https://www.td.gov.hk/filemanager/common/pvrm%20auction%20result%20handout%2020120331.pdf","dataset_key":"pvrm","auction_key":"pvrm::2012-03-31"},{"auction_date":"2012-03-31","single_line":"ALV1NLAM","double_line":null,"amount_hkd":5000,"pdf_url":"https://www.td.gov.hk/filemanager/common/pvrm%20auction%20result%20handout%2020120331.pdf","dataset_key":"pvrm","auction_key":"pvrm::2012-03-31"},{"auction_date":"2012-03-31","single_line":"J1N L1NG","double_line":["J1N","L1NG"],"amount_hkd":5000,"pdf_url":"https://www.td.gov.hk/filemanager/common/pvrm%20auction%20result%20handout%2020120331.pdf","dataset_key":"pvrm","auction_key":"pvrm::2012-03-31"}],"cached_rows":200}